cognite/correlation/__init__.py
cognite/correlation/correlation.py
cognite/correlation/plot.py
cognite_correlation-0.1.5.dist-info/LICENSE
cognite_correlation-0.1.5.dist-info/METADATA
cognite_correlation-0.1.5.dist-info/WHEEL
cognite_correlation-0.1.5.dist-info/top_level.txt
cognite_correlation-0.1.5.dist-info/RECORD
