Metadata-Version: 2.1
Name: cognite-correlation
Version: 0.1.5
Summary: UNKNOWN
Home-page: UNKNOWN
License: UNKNOWN
Platform: UNKNOWN
Requires-Python: >=3.6
Requires-Dist: pandas
Requires-Dist: numpy
Requires-Dist: matplotlib
